{
  "appIsExample": false,
  "appLayout": {
    "type": "DESKTOP"
  },
  "applicationDetail": {
    "appPositioning": {
      "type": "FIXED"
    },
    "navigationSetting": {},
    "themeSetting": {
      "appMaxWidth": "LARGE",
      "density": 1.0,
      "sizing": 1.0
    }
  },
  "applicationVersion": 2,
  "collapseInvisibleWidgets": true,
  "color": "#FFEBFB",
  "embedSetting": {
    "height": "720px",
    "showNavigationBar": true,
    "width": "1024px"
  },
  "evaluationVersion": 2,
  "icon": "globe",
  "pages": [
    {
      "id": "Page1",
      "isDefault": true
    },
    {
      "id": "My-bucket",
      "isDefault": false
    }
  ],
  "unpublishedAppLayout": {
    "type": "DESKTOP"
  },
  "unpublishedApplicationDetail": {
    "appPositioning": {
      "type": "FIXED"
    },
    "navigationSetting": {},
    "themeSetting": {
      "appMaxWidth": "LARGE",
      "density": 1.0,
      "sizing": 1.0
    }
  }
}